{
    "id": "org.kde.licentia",
    "branch": "master",
    "runtime": "org.kde.Platform",
    "runtime-version": "6.9",
    "sdk": "org.kde.Sdk",
    "command": "licentia",
    "tags": [
        "nightly"
    ],
    "desktop-file-name-suffix": " (Nightly)",
    "finish-args": [
        "--share=ipc",
        "--socket=fallback-x11",
        "--socket=wayland",
        "--device=dri",
        "--share=network"
    ],
    "modules": [
        {
            "name": "kirigami-addons",
            "config-opts": [
                "-DBUILD_TESTING=OFF",
                "-DCMAKE_BUILD_TYPE=RelWithDebInfo"
            ],
            "buildsystem": "cmake-ninja",
            "builddir": true,
            "sources": [
                {
                    "url": "https://download.kde.org/stable/kirigami-addons/kirigami-addons-1.7.0.tar.xz",
                    "sha256": "7d854975185cf740de486d84f1e2ec3e4eadb66ac9fb897214cba9ab8cc492b1",
                    "type": "archive",
                    "x-checker-data": {
                        "type": "anitya",
                        "project-id": 242933,
                        "stable-only": true,
                        "url-template": "https://download.kde.org/stable/kirigami-addons/kirigami-addons-$version.tar.xz"
                    }
                }
            ],
            "cleanup": [
                "/lib/cmake"
            ]
        },
        {
            "name": "licentia",
            "buildsystem": "cmake-ninja",
            "sources": [
                {
                    "type": "dir",
                    "path": "."
                }
            ]
        }
    ]
}
